{"nodes": [{"id": "api_subscription_redeem_post", "label": "POST /api/subscription/redeem", "file_type": "code", "source_file": "website/src/app/api/subscription/redeem/route.ts", "source_location": null, "source_url": null, "captured_at": null, "author": null, "contributor": null}], "edges": [{"source": "api_subscription_redeem_post", "target": "prisma_license_model", "relation": "shares_data_with", "confidence": "EXTRACTED", "confidence_score": 1.0, "source_file": "website/src/app/api/subscription/redeem/route.ts", "source_location": null, "weight": 1.0}, {"source": "api_subscription_redeem_post", "target": "prisma_subscription_model", "relation": "shares_data_with", "confidence": "EXTRACTED", "confidence_score": 1.0, "source_file": "website/src/app/api/subscription/redeem/route.ts", "source_location": null, "weight": 1.0}, {"source": "api_subscription_redeem_post", "target": "lib_auth_options", "relation": "references", "confidence": "EXTRACTED", "confidence_score": 1.0, "source_file": "website/src/app/api/subscription/redeem/route.ts", "source_location": null, "weight": 1.0}], "hyperedges": []}